.coveragerc
CHANGES.rst
LICENSE
MANIFEST.in
README.rst
setup.py
tox.ini
contents/README.txt
morepath_wiki/__init__.py
morepath_wiki/__main__.py
morepath_wiki/app.py
morepath_wiki/html.py
morepath_wiki/model.py
morepath_wiki/path.py
morepath_wiki/storage.py
morepath_wiki/view.py
morepath_wiki.egg-info/PKG-INFO
morepath_wiki.egg-info/SOURCES.txt
morepath_wiki.egg-info/dependency_links.txt
morepath_wiki.egg-info/entry_points.txt
morepath_wiki.egg-info/not-zip-safe
morepath_wiki.egg-info/requires.txt
morepath_wiki.egg-info/top_level.txt
morepath_wiki/tests/__init__.py
morepath_wiki/tests/test_wiki.py