Metadata-Version: 1.1
Name: morepath-wiki
Version: 0.1
Summary: A wiki demo for Morepath, based on the web micro-framework battle by Richard Jones
Home-page: https://github.com/morepath/morepath_wiki
Author: Morepath developers
Author-email: morepath@googlegroups.com
License: BSD
Keywords: morepath demo
Platform: UNKNOWN
Classifier: Intended Audience :: Developers
Classifier: Environment :: Web Environment
Classifier: License :: OSI Approved :: BSD License
Classifier: Topic :: Internet :: WWW/HTTP :: WSGI
Classifier: Programming Language :: Python :: 2
Classifier: Programming Language :: Python :: 2.7
Classifier: Programming Language :: Python :: 3
Classifier: Programming Language :: Python :: 3.4
Classifier: Programming Language :: Python :: 3.5
